AUTHORS.rst
CONTRIBUTING.rst
HISTORY.rst
LICENSE
MANIFEST.in
README.rst
setup.cfg
setup.py
docs/Makefile
docs/authors.rst
docs/conf.py
docs/contributing.rst
docs/history.rst
docs/index.rst
docs/installation.rst
docs/make.bat
docs/readme.rst
docs/usage.rst
span_labeler/__init__.py
span_labeler/cli.py
span_labeler/span_labeler.py
span_labeler.egg-info/PKG-INFO
span_labeler.egg-info/SOURCES.txt
span_labeler.egg-info/dependency_links.txt
span_labeler.egg-info/entry_points.txt
span_labeler.egg-info/not-zip-safe
span_labeler.egg-info/requires.txt
span_labeler.egg-info/top_level.txt
tests/test_span_labeler.py