Metadata-Version: 1.1
Name: span-labeler
Version: 0.1.0
Summary: none
Home-page: https://github.com/huntzhan/span_labeler
Author: Haoxun Zhan
Author-email: programmer.zhx@gmail.com
License: MIT license
Keywords: span_labeler
Platform: UNKNOWN
Classifier: Development Status :: 2 - Pre-Alpha
Classifier: Intended Audience :: Developers
Classifier: License :: OSI Approved :: MIT License
Classifier: Natural Language :: English
Classifier: Programming Language :: Python :: 2
Classifier: Programming Language :: Python :: 2.7
Classifier: Programming Language :: Python :: 3
Classifier: Programming Language :: Python :: 3.4
Classifier: Programming Language :: Python :: 3.5
Classifier: Programming Language :: Python :: 3.6
